MANIFEST.in
README.rst
requirements.txt
setup.py
chillaxd/__init__.py
chillaxd/chillax.py
chillaxd/chillaxd.py
chillaxd/commands.py
chillaxd/datanode.py
chillaxd/datatree.py
chillaxd/log.py
chillaxd.egg-info/PKG-INFO
chillaxd.egg-info/SOURCES.txt
chillaxd.egg-info/dependency_links.txt
chillaxd.egg-info/entry_points.txt
chillaxd.egg-info/pbr.json
chillaxd.egg-info/requires.txt
chillaxd.egg-info/top_level.txt
chillaxd/consensus/__init__.py
chillaxd/consensus/log.py
chillaxd/consensus/message.py
chillaxd/consensus/peer.py
chillaxd/consensus/raft.py
chillaxd/consensus/tests/__init__.py
chillaxd/consensus/tests/test_message.py
chillaxd/consensus/tests/test_peer.py
chillaxd/consensus/tests/test_raft.py