Metadata-Version: 1.1
Name: chillaxd
Version: 0.1a2
Summary: Distributed coordination framework based on ZeroMQ and RAFT consensus algorithm.
Home-page: https://github.com/ylamgarchal/chillaxd
Author: Yassine Lamgarchal
Author-email: lamgarchal.yassine@gmail.com
License: Apache v2.0
Platform: UNKNOWN
Classifier: Environment :: Console
Classifier: Intended Audience :: Developers
Classifier: Intended Audience :: Information Technology
Classifier: License :: OSI Approved :: Apache Software License
Classifier: Operating System :: POSIX :: Linux
Classifier: Programming Language :: Python :: 2.7
Classifier: Programming Language :: Python :: 3.4
Classifier: Topic :: System :: Distributed Computing
